pan_plyr/__init__.py
pan_plyr/pan_plyr.py
pan_plyr-0.2.1.dist-info/LICENSE.txt
pan_plyr-0.2.1.dist-info/METADATA
pan_plyr-0.2.1.dist-info/WHEEL
pan_plyr-0.2.1.dist-info/top_level.txt
pan_plyr-0.2.1.dist-info/RECORD
