Metadata-Version: 2.1
Name: pan-plyr
Version: 0.2.1
Summary: Pandas with dplyr style
Author: Seyed Pozveh
Author-email: s.pozveh@gmail.com
License: MIT
Classifier: Programming Language :: Python :: 3
Classifier: License :: OSI Approved :: MIT License
Classifier: Operating System :: OS Independent
License-File: LICENSE.txt
Requires-Dist: pandas
Requires-Dist: sqlite3
